Metadata-Version: 2.1
Name: odoo-addon-donation_mass
Version: 16.0.2.0.0.2
Summary: Ability to create mass from donation lines
Home-page: https://github.com/OCA/vertical-abbey
Author: Barroux Abbey, Akretion, Odoo Community Association (OCA)
Author-email: support@odoo-community.org
License: AGPL-3
Classifier: Programming Language :: Python
Classifier: Framework :: Odoo
Classifier: Framework :: Odoo :: 16.0
Classifier: License :: OSI Approved :: GNU Affero General Public License v3
Requires-Python: >=3.10
Requires-Dist: odoo-addon-donation<16.1dev,>=16.0dev
Requires-Dist: odoo-addon-mass<16.1dev,>=16.0dev
Requires-Dist: odoo<16.1dev,>=16.0a
